md2ltx/app/__init__.py
md2ltx/app/constants.py
md2ltx/app/main.py
md2ltx/app/python_evaluation.py
md2ltx-0.0.67.dist-info/licenses/LICENSE
md2ltx-0.0.67.dist-info/METADATA
md2ltx-0.0.67.dist-info/WHEEL
md2ltx-0.0.67.dist-info/entry_points.txt
md2ltx-0.0.67.dist-info/top_level.txt
md2ltx-0.0.67.dist-info/RECORD
